{
  "timestamp": "2026-01-02T01:45:03.909255",
  "l1": {
    "time": "2026-01-01 21:52:00",
    "speed": 481.0,
    "density": 1.58,
    "bt": 7.02,
    "bz_gsm": -4.87,
    "pressure_dyn": 0.611419565588
  },
  "goes": {
    "G19": {
      "time": "2026-01-02 01:42:00+00:00",
      "Hp": 56.12538528442383,
      "B_total": 67.93515014648438,
      "mlt": 16.6,
      "mlt_sector": "DUSK"
    },
    "G18": {
      "time": "2026-01-02 01:42:00+00:00",
      "Hp": 85.37538146972656,
      "B_total": 87.59727478027344,
      "mlt": 16.6,
      "mlt_sector": "DUSK"
    }
  },
  "detections": {
    "ip_shocks": [],
    "ssc_events": []
  },
  "published_at": "2026-01-02T01:45:17.136691Z"
}