{
  "timestamp": "2026-01-02T03:15:04.005422",
  "l1": {
    "time": "2026-01-02 03:12:00",
    "speed": 497.9,
    "density": 3.32,
    "bt": 6.5,
    "bz_gsm": -5.7,
    "pressure_dyn": 1.37662112167112
  },
  "goes": {
    "G19": {
      "time": "2026-01-02 03:12:00+00:00",
      "Hp": 59.95866012573242,
      "B_total": 71.30968475341797,
      "mlt": 18.1,
      "mlt_sector": "DUSK"
    },
    "G18": {
      "time": "2026-01-02 03:12:00+00:00",
      "Hp": 72.93619537353516,
      "B_total": 74.19099426269531,
      "mlt": 18.1,
      "mlt_sector": "DUSK"
    }
  },
  "detections": {
    "ip_shocks": [],
    "ssc_events": []
  },
  "published_at": "2026-01-02T03:15:10.845363Z"
}