{
  "timestamp": "2026-01-02T12:30:03.985524",
  "l1": {
    "time": "2026-01-02 12:28:00",
    "speed": 600.4,
    "density": 2.53,
    "bt": 6.75,
    "bz_gsm": -5.15,
    "pressure_dyn": 1.52543596250848
  },
  "goes": {
    "G19": {
      "time": "2026-01-02 12:28:00+00:00",
      "Hp": 93.18724060058594,
      "B_total": 98.02936553955078,
      "mlt": 3.366666666666667,
      "mlt_sector": "DAWN"
    },
    "G18": {
      "time": "2026-01-02 12:28:00+00:00",
      "Hp": 63.386802673339844,
      "B_total": 64.74557495117188,
      "mlt": 3.366666666666667,
      "mlt_sector": "DAWN"
    }
  },
  "detections": {
    "ip_shocks": [],
    "ssc_events": []
  },
  "published_at": "2026-01-02T12:30:44.666574Z"
}