{
  "timestamp": "2026-01-03T22:00:04.033723",
  "l1": {
    "time": "2026-01-03 21:56:00",
    "speed": 464.6,
    "density": 1.45,
    "bt": 4.91,
    "bz_gsm": 3.47,
    "pressure_dyn": 0.5235021933532
  },
  "goes": {
    "G19": {
      "time": "2026-01-03 21:58:00+00:00",
      "Hp": 93.58004760742188,
      "B_total": 100.15100860595703,
      "mlt": 12.866666666666665,
      "mlt_sector": "NOON"
    },
    "G18": {
      "time": "2026-01-03 21:58:00+00:00",
      "Hp": 107.63687896728516,
      "B_total": 109.74422454833984,
      "mlt": 12.866666666666665,
      "mlt_sector": "NOON"
    }
  },
  "detections": {
    "ip_shocks": [],
    "ssc_events": []
  },
  "published_at": "2026-01-03T22:01:15.349866Z"
}